kard_private_api/__init__.py
kard_private_api/v2.py
kard_private_api-2.1.dist-info/LICENSE
kard_private_api-2.1.dist-info/METADATA
kard_private_api-2.1.dist-info/WHEEL
kard_private_api-2.1.dist-info/top_level.txt
kard_private_api-2.1.dist-info/RECORD
