Metadata-Version: 2.1
Name: kard-private-api
Version: 2.1
Summary: Control and Automate your Kard account
Home-page: https://github.com/ghrlt/kard-private-api
Author: Gaëtan Hrlt
Author-email: gaetan.hrlt+dev@gmail.com
Project-URL: Developer website, https://ghr.lt?f=kard-private-api
Project-URL: Bug Tracker, https://github.com/ghrlt/kard-private-api/issues
Classifier: Programming Language :: Python :: 3
Classifier: License :: OSI Approved :: GNU General Public License v3 (GPLv3)
Classifier: Operating System :: OS Independent
Requires-Python: >=3.6
License-File: LICENSE
Requires-Dist: requests
